{
	"configurations" : 
	[
		{
			"directories" : 
			[
				{
					"build" : ".",
					"hasInstallRule" : true,
					"jsonFile" : "directory-.-eebaf8cb6174ea8609c6.json",
					"minimumCMakeVersion" : 
					{
						"string" : "3.15"
					},
					"projectIndex" : 0,
					"source" : ".",
					"targetIndexes" : 
					[
						0,
						1
					]
				}
			],
			"name" : "",
			"projects" : 
			[
				{
					"directoryIndexes" : 
					[
						0
					],
					"name" : "sirgas_description",
					"targetIndexes" : 
					[
						0,
						1
					]
				}
			],
			"targets" : 
			[
				{
					"directoryIndex" : 0,
					"id" : "sirgas_description_uninstall::@6890427a1f51a3e7e1df",
					"jsonFile" : "target-sirgas_description_uninstall-9e776c239d2aa219a752.json",
					"name" : "sirgas_description_uninstall",
					"projectIndex" : 0
				},
				{
					"directoryIndex" : 0,
					"id" : "uninstall::@6890427a1f51a3e7e1df",
					"jsonFile" : "target-uninstall-9134d7feaaf344a63f59.json",
					"name" : "uninstall",
					"projectIndex" : 0
				}
			]
		}
	],
	"kind" : "codemodel",
	"paths" : 
	{
		"build" : "/home/ev/RBE594_ws/build/sirgas_description",
		"source" : "/home/ev/RBE594_ws/src/sirgas_description"
	},
	"version" : 
	{
		"major" : 2,
		"minor" : 6
	}
}
